hmt_azure_funcs/__init__.py
hmt_azure_funcs/list_files_in_container.py
hmt_azure_funcs/read_buffer.py
hmt_azure_funcs/read_parquet.py
hmt_azure_funcs/read_parquet_from_container_default_credential.py
hmt_azure_funcs/upload_dataframe_to_parquet.py
hmt_azure_funcs/write_buffer.py
hmt_azure_funcs/write_parquet_to_container_default_credential.py
hmt_azure_funcs-0.6.1.dist-info/METADATA
hmt_azure_funcs-0.6.1.dist-info/WHEEL
hmt_azure_funcs-0.6.1.dist-info/top_level.txt
hmt_azure_funcs-0.6.1.dist-info/RECORD
